MANIFEST.in
README.rst
setup.cfg
setup.py
publicationstats/__init__.py
publicationstats/client.py
publicationstats/queries.py
publicationstats/utils.py
publicationstats/thrift/publication_stats.thrift
publicationstatsapi.egg-info/PKG-INFO
publicationstatsapi.egg-info/SOURCES.txt
publicationstatsapi.egg-info/dependency_links.txt
publicationstatsapi.egg-info/requires.txt
publicationstatsapi.egg-info/top_level.txt
tests/__init__.py
tests/test_accessstats.py
tests/test_queries.py